{
  "summary_version": "SIG_SHADOW_01B_SUMMARY_v1_0",
  "created_utc": "2026-07-11T07:57:44Z",
  "authority": "SIG_SHADOW_01B_SUMMARY_BUILDER_v1_0|SHADOW_ONLY|NOT_SIGNAL|NO_ENTRY_STOP_TARGET|NO_BROKER_EXECUTION",
  "shadow_status": "UPDATED",
  "candidate_count": 727,
  "blocked_candidate_count": 1,
  "observation_count": 727,
  "observed_complete_count": 0,
  "pending_observation_count": 727,
  "by_cluster": {
    "SCU01_CLUSTER_H1_WEEKLY_OPEN_REACTION": 92,
    "SCU01_CLUSTER_H1_HTF_ALIGNMENT_CONTINUATION": 12,
    "SCU01_CLUSTER_H1_COUNTER_HTF_RECLAIM": 269,
    "SCU01_CLUSTER_H1_FAILED_BREAKOUT_TRAP": 30,
    "SCU01_CLUSTER_H1_COUNTER_HTF_REJECTION": 171,
    "SETUP_CLUSTER_H1_LONDON_NY_OVERLAP_SESSION_OPEN_TREND_v1_0": 26,
    "SCU01_CLUSTER_H1_SESSION_OPEN_TREND": 45,
    "SCU01_CLUSTER_H1_VOL_EXPANSION_AFTER_CONTRACTION": 82
  },
  "by_instrument": {
    "XAUUSD": 309,
    "EURUSD": 161,
    "USDJPY": 257
  },
  "observation_states": {
    "PENDING_OBSERVATION": 727
  },
  "recent_candidates": [
    {
      "candidate_id": "SCUSHADOW_05a7327f9ea367fb419816",
      "candidate_version": "SHADOW_CANDIDATE_UNIVERSE_01_INTAKE_v1_0",
      "candidate_state": "SHADOW_UNIVERSE_ACTIVE_PENDING_OBSERVATION_NOT_SIGNAL",
      "candidate_contract_id": "SCU01_H1_COUNTER_HTF_REJECTION_CONTRACT_v1_0",
      "setup_cluster_id": "SCU01_CLUSTER_H1_COUNTER_HTF_REJECTION",
      "source_memory_ids": [],
      "source_candidate_id": "SCU01_USDJPY_H1_COUNTER_H4_BEARISH_REJECTION_SHORT_v1_0",
      "source_shadow_event_id": "SCU_EVT_f0c70a634c526b0169f8f925",
      "source_candidate_family": "H1_COUNTER_HTF_REJECTION",
      "source_type": "SHADOW_CANDIDATE_UNIVERSE_01_RESEARCH_ONLY",
      "instrument": "USDJPY",
      "timeframe": "H1",
      "directional_bias": "SHORT_BIAS",
      "created_utc": "2026-07-10T14:57:26Z",
      "trigger_bar_open_ts_utc": "2026-07-10T13:00:00Z",
      "valid_until_utc": "2026-07-10T21:00:00Z",
      "shadow_horizons": [
        "H1+1",
        "H1+2",
        "H1+4",
        "H1+8"
      ],
      "observation_reference_price": 161.79777,
      "observation_reference_price_policy": "closed H1 context h1_close; observation-only, not entry",
      "source_payload_created_utc": "2026-07-10T14:57:15Z",
      "source_payload_version": "SIG_BRAIN4_RUNTIME_PAYLOAD_v1_4_EVENT_LIFECYCLE_OPS21",
      "quality_band_not_probability": "PRE_REGISTERED_SHADOW_ONLY_NO_EDGE_CLAIM",
      "source_evidence": [
        {
          "source_candidate_id": "SCU01_USDJPY_H1_COUNTER_H4_BEARISH_REJECTION_SHORT_v1_0",
          "candidate_family": "H1_COUNTER_HTF_REJECTION",
          "evaluation_status": "SHADOW_CANDIDATE_ACTIVE",
          "score_not_probability": 43,
          "passed_clause_count": 4,
          "total_clause_count": 4,
          "evidence_grade": "NO_EDGE_CLAIM_FORWARD_OBSERVATION_ONLY"
        }
      ],
      "latest_context_excerpt": {
        "instrument": "USDJPY",
        "timeframe": "H1",
        "latest_bar_open_ts_utc": "2026-07-10T13:00:00Z",
        "latest_h1_bar_open_ts_utc": "2026-07-10T13:00:00Z",
        "session_bucket": "LONDON_NY_OVERLAP",
        "h1_bar_direction": "BEARISH",
        "d1_trend_state": "FLAT",
        "h4_trend_state": "UP",
        "is_first_h1_bar_of_session": false,
        "last4_h1_contraction_flag": true,
        "current_h1_expansion_flag": false,
        "asian_high_breakout_continuation_by_closed_h1": null,
        "asian_high_swept_and_reclaimed_by_closed_h1": null,
        "weekly_open_reclaim_short_state": "NONE",
        "h1_close": 161.79777,
        "data_sufficiency_status": "OK",
        "context_builder_status": "DERIVED_FROM_READ_ONLY_CLOSED_H1_H4_D1_BARS_OPS20"
      },
      "authority": "SHADOW_CANDIDATE_UNIVERSE_01|RESEARCH_SHADOW_ONLY|NOT_SIGNAL|NO_BUY_SELL|NO_ENTRY_STOP_TARGET|NO_POSITION_SIZE|NO_BROKER_EXECUTION|NO_AUTO_LEARNING|NO_RULE_REWRITE",
      "signal_authorized": false,
      "trade_instruction_authorized": false,
      "broker_execution_authorized": false,
      "action_surface_authorized": false,
      "auto_learning_authorized": false,
      "rule_rewrite_authorized": false,
      "forbidden_interpretation": "Research-only shadow candidate. Do not read as buy/sell/entry/stop/target/profitability/tradability/broker execution.",
      "shadow_ledger_state": "SHADOW_REGISTERED_PENDING_OBSERVATION",
      "first_seen_utc": "2026-07-10T14:07:32Z",
      "last_seen_utc": "2026-07-10T14:57:26Z",
      "seen_refresh_count": 11,
      "ledger_authority": "SIG_SHADOW_01B_LEDGER_BUILDER_v1_0|FORWARD_SHADOW_ONLY|NOT_SIGNAL|NO_BUY_SELL|NO_ENTRY_STOP_TARGET|NO_POSITION_SIZE|NO_BROKER_EXECUTION"
    },
    {
      "candidate_id": "SCUSHADOW_22f48c891ee2ee021ebd11",
      "candidate_version": "SHADOW_CANDIDATE_UNIVERSE_01_INTAKE_v1_0",
      "candidate_state": "SHADOW_UNIVERSE_ACTIVE_PENDING_OBSERVATION_NOT_SIGNAL",
      "candidate_contract_id": "SCU01_H1_COUNTER_HTF_RECLAIM_CONTRACT_v1_0",
      "setup_cluster_id": "SCU01_CLUSTER_H1_COUNTER_HTF_RECLAIM",
      "source_memory_ids": [],
      "source_candidate_id": "SCU01_EURUSD_H1_COUNTER_H4_BULLISH_RECLAIM_LONG_v1_0",
      "source_shadow_event_id": "SCU_EVT_5cb3b8d789de3e923388756b",
      "source_candidate_family": "H1_COUNTER_HTF_RECLAIM",
      "source_type": "SHADOW_CANDIDATE_UNIVERSE_01_RESEARCH_ONLY",
      "instrument": "EURUSD",
      "timeframe": "H1",
      "directional_bias": "LONG_BIAS",
      "created_utc": "2026-07-10T15:57:26Z",
      "trigger_bar_open_ts_utc": "2026-07-10T14:00:00Z",
      "valid_until_utc": "2026-07-10T22:00:00Z",
      "shadow_horizons": [
        "H1+1",
        "H1+2",
        "H1+4",
        "H1+8"
      ],
      "observation_reference_price": 1.14223,
      "observation_reference_price_policy": "closed H1 context h1_close; observation-only, not entry",
      "source_payload_created_utc": "2026-07-10T15:57:15Z",
      "source_payload_version": "SIG_BRAIN4_RUNTIME_PAYLOAD_v1_4_EVENT_LIFECYCLE_OPS21",
      "quality_band_not_probability": "PRE_REGISTERED_SHADOW_ONLY_NO_EDGE_CLAIM",
      "source_evidence": [
        {
          "source_candidate_id": "SCU01_EURUSD_H1_COUNTER_H4_BULLISH_RECLAIM_LONG_v1_0",
          "candidate_family": "H1_COUNTER_HTF_RECLAIM",
          "evaluation_status": "SHADOW_CANDIDATE_ACTIVE",
          "score_not_probability": 43,
          "passed_clause_count": 4,
          "total_clause_count": 4,
          "evidence_grade": "NO_EDGE_CLAIM_FORWARD_OBSERVATION_ONLY"
        }
      ],
      "latest_context_excerpt": {
        "instrument": "EURUSD",
        "timeframe": "H1",
        "latest_bar_open_ts_utc": "2026-07-10T14:00:00Z",
        "latest_h1_bar_open_ts_utc": "2026-07-10T14:00:00Z",
        "session_bucket": "LONDON_NY_OVERLAP",
        "h1_bar_direction": "BULLISH",
        "d1_trend_state": "FLAT",
        "h4_trend_state": "DOWN",
        "is_first_h1_bar_of_session": false,
        "last4_h1_contraction_flag": false,
        "current_h1_expansion_flag": false,
        "asian_high_breakout_continuation_by_closed_h1": null,
        "asian_high_swept_and_reclaimed_by_closed_h1": null,
        "london_low_swept_and_reclaimed_by_closed_h1": null,
        "weekly_open_reclaim_short_state": "NONE",
        "h1_failed_breakout_or_session_sweep_state": "NONE",
        "h1_close": 1.14223,
        "data_sufficiency_status": "OK",
        "context_builder_status": "DERIVED_FROM_READ_ONLY_CLOSED_H1_H4_D1_BARS_OPS20"
      },
      "authority": "SHADOW_CANDIDATE_UNIVERSE_01|RESEARCH_SHADOW_ONLY|NOT_SIGNAL|NO_BUY_SELL|NO_ENTRY_STOP_TARGET|NO_POSITION_SIZE|NO_BROKER_EXECUTION|NO_AUTO_LEARNING|NO_RULE_REWRITE",
      "signal_authorized": false,
      "trade_instruction_authorized": false,
      "broker_execution_authorized": false,
      "action_surface_authorized": false,
      "auto_learning_authorized": false,
      "rule_rewrite_authorized": false,
      "forbidden_interpretation": "Research-only shadow candidate. Do not read as buy/sell/entry/stop/target/profitability/tradability/broker execution.",
      "shadow_ledger_state": "SHADOW_REGISTERED_PENDING_OBSERVATION",
      "first_seen_utc": "2026-07-10T15:07:30Z",
      "last_seen_utc": "2026-07-10T15:57:26Z",
      "seen_refresh_count": 11,
      "ledger_authority": "SIG_SHADOW_01B_LEDGER_BUILDER_v1_0|FORWARD_SHADOW_ONLY|NOT_SIGNAL|NO_BUY_SELL|NO_ENTRY_STOP_TARGET|NO_POSITION_SIZE|NO_BROKER_EXECUTION"
    },
    {
      "candidate_id": "SCUSHADOW_3b493c7d7f6bd52ed6659e",
      "candidate_version": "SHADOW_CANDIDATE_UNIVERSE_01_INTAKE_v1_0",
      "candidate_state": "SHADOW_UNIVERSE_ACTIVE_PENDING_OBSERVATION_NOT_SIGNAL",
      "candidate_contract_id": "SCU01_H1_VOL_EXPANSION_AFTER_CONTRACTION_CONTRACT_v1_0",
      "setup_cluster_id": "SCU01_CLUSTER_H1_VOL_EXPANSION_AFTER_CONTRACTION",
      "source_memory_ids": [],
      "source_candidate_id": "SCU01_XAUUSD_H1_VOL_EXPANSION_AFTER_CONTRACTION_SHORT_v1_0",
      "source_shadow_event_id": "SCU_EVT_7619c4bf7c1c0bcedb40de02",
      "source_candidate_family": "H1_VOL_EXPANSION_AFTER_CONTRACTION",
      "source_type": "SHADOW_CANDIDATE_UNIVERSE_01_RESEARCH_ONLY",
      "instrument": "XAUUSD",
      "timeframe": "H1",
      "directional_bias": "SHORT_BIAS",
      "created_utc": "2026-07-10T15:57:26Z",
      "trigger_bar_open_ts_utc": "2026-07-10T14:00:00Z",
      "valid_until_utc": "2026-07-10T22:00:00Z",
      "shadow_horizons": [
        "H1+1",
        "H1+2",
        "H1+4",
        "H1+8"
      ],
      "observation_reference_price": 4092.77043,
      "observation_reference_price_policy": "closed H1 context h1_close; observation-only, not entry",
      "source_payload_created_utc": "2026-07-10T15:57:15Z",
      "source_payload_version": "SIG_BRAIN4_RUNTIME_PAYLOAD_v1_4_EVENT_LIFECYCLE_OPS21",
      "quality_band_not_probability": "PRE_REGISTERED_SHADOW_ONLY_NO_EDGE_CLAIM",
      "source_evidence": [
        {
          "source_candidate_id": "SCU01_XAUUSD_H1_VOL_EXPANSION_AFTER_CONTRACTION_SHORT_v1_0",
          "candidate_family": "H1_VOL_EXPANSION_AFTER_CONTRACTION",
          "evaluation_status": "SHADOW_CANDIDATE_ACTIVE",
          "score_not_probability": 50,
          "passed_clause_count": 5,
          "total_clause_count": 5,
          "evidence_grade": "NO_EDGE_CLAIM_FORWARD_OBSERVATION_ONLY"
        }
      ],
      "latest_context_excerpt": {
        "instrument": "XAUUSD",
        "timeframe": "H1",
        "latest_bar_open_ts_utc": "2026-07-10T14:00:00Z",
        "latest_h1_bar_open_ts_utc": "2026-07-10T14:00:00Z",
        "session_bucket": "LONDON_NY_OVERLAP",
        "h1_bar_direction": "BEARISH",
        "d1_trend_state": "UP",
        "h4_trend_state": "DOWN",
        "is_first_h1_bar_of_session": false,
        "last4_h1_contraction_flag": true,
        "current_h1_expansion_flag": true,
        "asian_high_breakout_continuation_by_closed_h1": null,
        "asian_high_swept_and_reclaimed_by_closed_h1": null,
        "weekly_open_reclaim_short_state": "WEEKLY_OPEN_RECLAIM_SHORT",
        "h1_close": 4092.77043,
        "data_sufficiency_status": "OK",
        "context_builder_status": "DERIVED_FROM_READ_ONLY_CLOSED_H1_H4_D1_BARS_OPS20"
      },
      "authority": "SHADOW_CANDIDATE_UNIVERSE_01|RESEARCH_SHADOW_ONLY|NOT_SIGNAL|NO_BUY_SELL|NO_ENTRY_STOP_TARGET|NO_POSITION_SIZE|NO_BROKER_EXECUTION|NO_AUTO_LEARNING|NO_RULE_REWRITE",
      "signal_authorized": false,
      "trade_instruction_authorized": false,
      "broker_execution_authorized": false,
      "action_surface_authorized": false,
      "auto_learning_authorized": false,
      "rule_rewrite_authorized": false,
      "forbidden_interpretation": "Research-only shadow candidate. Do not read as buy/sell/entry/stop/target/profitability/tradability/broker execution.",
      "shadow_ledger_state": "SHADOW_REGISTERED_PENDING_OBSERVATION",
      "first_seen_utc": "2026-07-10T15:07:30Z",
      "last_seen_utc": "2026-07-10T15:57:26Z",
      "seen_refresh_count": 11,
      "ledger_authority": "SIG_SHADOW_01B_LEDGER_BUILDER_v1_0|FORWARD_SHADOW_ONLY|NOT_SIGNAL|NO_BUY_SELL|NO_ENTRY_STOP_TARGET|NO_POSITION_SIZE|NO_BROKER_EXECUTION"
    },
    {
      "candidate_id": "SCUSHADOW_b39f523ee59adc8b338a07",
      "candidate_version": "SHADOW_CANDIDATE_UNIVERSE_01_INTAKE_v1_0",
      "candidate_state": "SHADOW_UNIVERSE_ACTIVE_PENDING_OBSERVATION_NOT_SIGNAL",
      "candidate_contract_id": "SCU01_H1_WEEKLY_OPEN_REACTION_CONTRACT_v1_0",
      "setup_cluster_id": "SCU01_CLUSTER_H1_WEEKLY_OPEN_REACTION",
      "source_memory_ids": [],
      "source_candidate_id": "SCU01_XAUUSD_H1_WEEKLY_OPEN_RECLAIM_SHORT_v1_0",
      "source_shadow_event_id": "SCU_EVT_8c0febba5a00961c748741d4",
      "source_candidate_family": "H1_WEEKLY_OPEN_REACTION",
      "source_type": "SHADOW_CANDIDATE_UNIVERSE_01_RESEARCH_ONLY",
      "instrument": "XAUUSD",
      "timeframe": "H1",
      "directional_bias": "SHORT_BIAS",
      "created_utc": "2026-07-10T15:57:26Z",
      "trigger_bar_open_ts_utc": "2026-07-10T14:00:00Z",
      "valid_until_utc": "2026-07-10T22:00:00Z",
      "shadow_horizons": [
        "H1+1",
        "H1+2",
        "H1+4",
        "H1+8"
      ],
      "observation_reference_price": 4092.77043,
      "observation_reference_price_policy": "closed H1 context h1_close; observation-only, not entry",
      "source_payload_created_utc": "2026-07-10T15:57:15Z",
      "source_payload_version": "SIG_BRAIN4_RUNTIME_PAYLOAD_v1_4_EVENT_LIFECYCLE_OPS21",
      "quality_band_not_probability": "PRE_REGISTERED_SHADOW_ONLY_NO_EDGE_CLAIM",
      "source_evidence": [
        {
          "source_candidate_id": "SCU01_XAUUSD_H1_WEEKLY_OPEN_RECLAIM_SHORT_v1_0",
          "candidate_family": "H1_WEEKLY_OPEN_REACTION",
          "evaluation_status": "SHADOW_CANDIDATE_ACTIVE",
          "score_not_probability": 47,
          "passed_clause_count": 5,
          "total_clause_count": 5,
          "evidence_grade": "NO_EDGE_CLAIM_FORWARD_OBSERVATION_ONLY"
        }
      ],
      "latest_context_excerpt": {
        "instrument": "XAUUSD",
        "timeframe": "H1",
        "latest_bar_open_ts_utc": "2026-07-10T14:00:00Z",
        "latest_h1_bar_open_ts_utc": "2026-07-10T14:00:00Z",
        "session_bucket": "LONDON_NY_OVERLAP",
        "h1_bar_direction": "BEARISH",
        "d1_trend_state": "UP",
        "h4_trend_state": "DOWN",
        "is_first_h1_bar_of_session": false,
        "last4_h1_contraction_flag": true,
        "current_h1_expansion_flag": true,
        "asian_high_breakout_continuation_by_closed_h1": null,
        "asian_high_swept_and_reclaimed_by_closed_h1": null,
        "weekly_open_reclaim_short_state": "WEEKLY_OPEN_RECLAIM_SHORT",
        "h1_close": 4092.77043,
        "data_sufficiency_status": "OK",
        "context_builder_status": "DERIVED_FROM_READ_ONLY_CLOSED_H1_H4_D1_BARS_OPS20"
      },
      "authority": "SHADOW_CANDIDATE_UNIVERSE_01|RESEARCH_SHADOW_ONLY|NOT_SIGNAL|NO_BUY_SELL|NO_ENTRY_STOP_TARGET|NO_POSITION_SIZE|NO_BROKER_EXECUTION|NO_AUTO_LEARNING|NO_RULE_REWRITE",
      "signal_authorized": false,
      "trade_instruction_authorized": false,
      "broker_execution_authorized": false,
      "action_surface_authorized": false,
      "auto_learning_authorized": false,
      "rule_rewrite_authorized": false,
      "forbidden_interpretation": "Research-only shadow candidate. Do not read as buy/sell/entry/stop/target/profitability/tradability/broker execution.",
      "shadow_ledger_state": "SHADOW_REGISTERED_PENDING_OBSERVATION",
      "first_seen_utc": "2026-07-10T15:07:30Z",
      "last_seen_utc": "2026-07-10T15:57:26Z",
      "seen_refresh_count": 11,
      "ledger_authority": "SIG_SHADOW_01B_LEDGER_BUILDER_v1_0|FORWARD_SHADOW_ONLY|NOT_SIGNAL|NO_BUY_SELL|NO_ENTRY_STOP_TARGET|NO_POSITION_SIZE|NO_BROKER_EXECUTION"
    },
    {
      "candidate_id": "SCUSHADOW_a8a090a0c6a29db5ce08da",
      "candidate_version": "SHADOW_CANDIDATE_UNIVERSE_01_INTAKE_v1_0",
      "candidate_state": "SHADOW_UNIVERSE_ACTIVE_PENDING_OBSERVATION_NOT_SIGNAL",
      "candidate_contract_id": "SCU01_H1_COUNTER_HTF_REJECTION_CONTRACT_v1_0",
      "setup_cluster_id": "SCU01_CLUSTER_H1_COUNTER_HTF_REJECTION",
      "source_memory_ids": [],
      "source_candidate_id": "SCU01_USDJPY_H1_COUNTER_H4_BEARISH_REJECTION_SHORT_v1_0",
      "source_shadow_event_id": "SCU_EVT_cf9a251e3e0fd8edf7ec56ac",
      "source_candidate_family": "H1_COUNTER_HTF_REJECTION",
      "source_type": "SHADOW_CANDIDATE_UNIVERSE_01_RESEARCH_ONLY",
      "instrument": "USDJPY",
      "timeframe": "H1",
      "directional_bias": "SHORT_BIAS",
      "created_utc": "2026-07-10T16:57:39Z",
      "trigger_bar_open_ts_utc": "2026-07-10T15:00:00Z",
      "valid_until_utc": "2026-07-10T23:00:00Z",
      "shadow_horizons": [
        "H1+1",
        "H1+2",
        "H1+4",
        "H1+8"
      ],
      "observation_reference_price": 161.30851,
      "observation_reference_price_policy": "closed H1 context h1_close; observation-only, not entry",
      "source_payload_created_utc": "2026-07-10T16:57:17Z",
      "source_payload_version": "SIG_BRAIN4_RUNTIME_PAYLOAD_v1_4_EVENT_LIFECYCLE_OPS21",
      "quality_band_not_probability": "PRE_REGISTERED_SHADOW_ONLY_NO_EDGE_CLAIM",
      "source_evidence": [
        {
          "source_candidate_id": "SCU01_USDJPY_H1_COUNTER_H4_BEARISH_REJECTION_SHORT_v1_0",
          "candidate_family": "H1_COUNTER_HTF_REJECTION",
          "evaluation_status": "SHADOW_CANDIDATE_ACTIVE",
          "score_not_probability": 43,
          "passed_clause_count": 4,
          "total_clause_count": 4,
          "evidence_grade": "NO_EDGE_CLAIM_FORWARD_OBSERVATION_ONLY"
        }
      ],
      "latest_context_excerpt": {
        "instrument": "USDJPY",
        "timeframe": "H1",
        "latest_bar_open_ts_utc": "2026-07-10T15:00:00Z",
        "latest_h1_bar_open_ts_utc": "2026-07-10T15:00:00Z",
        "session_bucket": "LONDON_NY_OVERLAP",
        "h1_bar_direction": "BEARISH",
        "d1_trend_state": "FLAT",
        "h4_trend_state": "UP",
        "is_first_h1_bar_of_session": false,
        "last4_h1_contraction_flag": true,
        "current_h1_expansion_flag": true,
        "asian_high_breakout_continuation_by_closed_h1": null,
        "asian_high_swept_and_reclaimed_by_closed_h1": null,
        "weekly_open_reclaim_short_state": "NONE",
        "h1_close": 161.30851,
        "data_sufficiency_status": "OK",
        "context_builder_status": "DERIVED_FROM_READ_ONLY_CLOSED_H1_H4_D1_BARS_OPS20"
      },
      "authority": "SHADOW_CANDIDATE_UNIVERSE_01|RESEARCH_SHADOW_ONLY|NOT_SIGNAL|NO_BUY_SELL|NO_ENTRY_STOP_TARGET|NO_POSITION_SIZE|NO_BROKER_EXECUTION|NO_AUTO_LEARNING|NO_RULE_REWRITE",
      "signal_authorized": false,
      "trade_instruction_authorized": false,
      "broker_execution_authorized": false,
      "action_surface_authorized": false,
      "auto_learning_authorized": false,
      "rule_rewrite_authorized": false,
      "forbidden_interpretation": "Research-only shadow candidate. Do not read as buy/sell/entry/stop/target/profitability/tradability/broker execution.",
      "shadow_ledger_state": "SHADOW_REGISTERED_PENDING_OBSERVATION",
      "first_seen_utc": "2026-07-10T16:07:27Z",
      "last_seen_utc": "2026-07-10T16:57:40Z",
      "seen_refresh_count": 9,
      "ledger_authority": "SIG_SHADOW_01B_LEDGER_BUILDER_v1_0|FORWARD_SHADOW_ONLY|NOT_SIGNAL|NO_BUY_SELL|NO_ENTRY_STOP_TARGET|NO_POSITION_SIZE|NO_BROKER_EXECUTION"
    },
    {
      "candidate_id": "SCUSHADOW_d9af72521010e9f511b2ff",
      "candidate_version": "SHADOW_CANDIDATE_UNIVERSE_01_INTAKE_v1_0",
      "candidate_state": "SHADOW_UNIVERSE_ACTIVE_PENDING_OBSERVATION_NOT_SIGNAL",
      "candidate_contract_id": "SCU01_H1_COUNTER_HTF_RECLAIM_CONTRACT_v1_0",
      "setup_cluster_id": "SCU01_CLUSTER_H1_COUNTER_HTF_RECLAIM",
      "source_memory_ids": [],
      "source_candidate_id": "SCU01_XAUUSD_H1_COUNTER_H4_BULLISH_RECLAIM_LONG_v1_0",
      "source_shadow_event_id": "SCU_EVT_73050dd97f598bf7067e528b",
      "source_candidate_family": "H1_COUNTER_HTF_RECLAIM",
      "source_type": "SHADOW_CANDIDATE_UNIVERSE_01_RESEARCH_ONLY",
      "instrument": "XAUUSD",
      "timeframe": "H1",
      "directional_bias": "LONG_BIAS",
      "created_utc": "2026-07-10T16:57:39Z",
      "trigger_bar_open_ts_utc": "2026-07-10T15:00:00Z",
      "valid_until_utc": "2026-07-10T23:00:00Z",
      "shadow_horizons": [
        "H1+1",
        "H1+2",
        "H1+4",
        "H1+8"
      ],
      "observation_reference_price": 4112.09646,
      "observation_reference_price_policy": "closed H1 context h1_close; observation-only, not entry",
      "source_payload_created_utc": "2026-07-10T16:57:17Z",
      "source_payload_version": "SIG_BRAIN4_RUNTIME_PAYLOAD_v1_4_EVENT_LIFECYCLE_OPS21",
      "quality_band_not_probability": "PRE_REGISTERED_SHADOW_ONLY_NO_EDGE_CLAIM",
      "source_evidence": [
        {
          "source_candidate_id": "SCU01_XAUUSD_H1_COUNTER_H4_BULLISH_RECLAIM_LONG_v1_0",
          "candidate_family": "H1_COUNTER_HTF_RECLAIM",
          "evaluation_status": "SHADOW_CANDIDATE_ACTIVE",
          "score_not_probability": 43,
          "passed_clause_count": 4,
          "total_clause_count": 4,
          "evidence_grade": "NO_EDGE_CLAIM_FORWARD_OBSERVATION_ONLY"
        }
      ],
      "latest_context_excerpt": {
        "instrument": "XAUUSD",
        "timeframe": "H1",
        "latest_bar_open_ts_utc": "2026-07-10T15:00:00Z",
        "latest_h1_bar_open_ts_utc": "2026-07-10T15:00:00Z",
        "session_bucket": "LONDON_NY_OVERLAP",
        "h1_bar_direction": "BULLISH",
        "d1_trend_state": "UP",
        "h4_trend_state": "DOWN",
        "is_first_h1_bar_of_session": false,
        "last4_h1_contraction_flag": false,
        "current_h1_expansion_flag": false,
        "asian_high_breakout_continuation_by_closed_h1": null,
        "asian_high_swept_and_reclaimed_by_closed_h1": null,
        "weekly_open_reclaim_short_state": "NONE",
        "h1_close": 4112.09646,
        "data_sufficiency_status": "OK",
        "context_builder_status": "DERIVED_FROM_READ_ONLY_CLOSED_H1_H4_D1_BARS_OPS20"
      },
      "authority": "SHADOW_CANDIDATE_UNIVERSE_01|RESEARCH_SHADOW_ONLY|NOT_SIGNAL|NO_BUY_SELL|NO_ENTRY_STOP_TARGET|NO_POSITION_SIZE|NO_BROKER_EXECUTION|NO_AUTO_LEARNING|NO_RULE_REWRITE",
      "signal_authorized": false,
      "trade_instruction_authorized": false,
      "broker_execution_authorized": false,
      "action_surface_authorized": false,
      "auto_learning_authorized": false,
      "rule_rewrite_authorized": false,
      "forbidden_interpretation": "Research-only shadow candidate. Do not read as buy/sell/entry/stop/target/profitability/tradability/broker execution.",
      "shadow_ledger_state": "SHADOW_REGISTERED_PENDING_OBSERVATION",
      "first_seen_utc": "2026-07-10T16:07:27Z",
      "last_seen_utc": "2026-07-10T16:57:40Z",
      "seen_refresh_count": 9,
      "ledger_authority": "SIG_SHADOW_01B_LEDGER_BUILDER_v1_0|FORWARD_SHADOW_ONLY|NOT_SIGNAL|NO_BUY_SELL|NO_ENTRY_STOP_TARGET|NO_POSITION_SIZE|NO_BROKER_EXECUTION"
    },
    {
      "candidate_id": "SCUSHADOW_febdaf442d83f45fc8c3b6",
      "candidate_version": "SHADOW_CANDIDATE_UNIVERSE_01_INTAKE_v1_0",
      "candidate_state": "SHADOW_UNIVERSE_ACTIVE_PENDING_OBSERVATION_NOT_SIGNAL",
      "candidate_contract_id": "SCU01_H1_VOL_EXPANSION_AFTER_CONTRACTION_CONTRACT_v1_0",
      "setup_cluster_id": "SCU01_CLUSTER_H1_VOL_EXPANSION_AFTER_CONTRACTION",
      "source_memory_ids": [],
      "source_candidate_id": "SCU01_USDJPY_H1_VOL_EXPANSION_AFTER_CONTRACTION_SHORT_v1_0",
      "source_shadow_event_id": "SCU_EVT_a8b11deca8027b1160fe31bd",
      "source_candidate_family": "H1_VOL_EXPANSION_AFTER_CONTRACTION",
      "source_type": "SHADOW_CANDIDATE_UNIVERSE_01_RESEARCH_ONLY",
      "instrument": "USDJPY",
      "timeframe": "H1",
      "directional_bias": "SHORT_BIAS",
      "created_utc": "2026-07-10T16:57:39Z",
      "trigger_bar_open_ts_utc": "2026-07-10T15:00:00Z",
      "valid_until_utc": "2026-07-10T23:00:00Z",
      "shadow_horizons": [
        "H1+1",
        "H1+2",
        "H1+4",
        "H1+8"
      ],
      "observation_reference_price": 161.30851,
      "observation_reference_price_policy": "closed H1 context h1_close; observation-only, not entry",
      "source_payload_created_utc": "2026-07-10T16:57:17Z",
      "source_payload_version": "SIG_BRAIN4_RUNTIME_PAYLOAD_v1_4_EVENT_LIFECYCLE_OPS21",
      "quality_band_not_probability": "PRE_REGISTERED_SHADOW_ONLY_NO_EDGE_CLAIM",
      "source_evidence": [
        {
          "source_candidate_id": "SCU01_USDJPY_H1_VOL_EXPANSION_AFTER_CONTRACTION_SHORT_v1_0",
          "candidate_family": "H1_VOL_EXPANSION_AFTER_CONTRACTION",
          "evaluation_status": "SHADOW_CANDIDATE_ACTIVE",
          "score_not_probability": 50,
          "passed_clause_count": 5,
          "total_clause_count": 5,
          "evidence_grade": "NO_EDGE_CLAIM_FORWARD_OBSERVATION_ONLY"
        }
      ],
      "latest_context_excerpt": {
        "instrument": "USDJPY",
        "timeframe": "H1",
        "latest_bar_open_ts_utc": "2026-07-10T15:00:00Z",
        "latest_h1_bar_open_ts_utc": "2026-07-10T15:00:00Z",
        "session_bucket": "LONDON_NY_OVERLAP",
        "h1_bar_direction": "BEARISH",
        "d1_trend_state": "FLAT",
        "h4_trend_state": "UP",
        "is_first_h1_bar_of_session": false,
        "last4_h1_contraction_flag": true,
        "current_h1_expansion_flag": true,
        "asian_high_breakout_continuation_by_closed_h1": null,
        "asian_high_swept_and_reclaimed_by_closed_h1": null,
        "weekly_open_reclaim_short_state": "NONE",
        "h1_close": 161.30851,
        "data_sufficiency_status": "OK",
        "context_builder_status": "DERIVED_FROM_READ_ONLY_CLOSED_H1_H4_D1_BARS_OPS20"
      },
      "authority": "SHADOW_CANDIDATE_UNIVERSE_01|RESEARCH_SHADOW_ONLY|NOT_SIGNAL|NO_BUY_SELL|NO_ENTRY_STOP_TARGET|NO_POSITION_SIZE|NO_BROKER_EXECUTION|NO_AUTO_LEARNING|NO_RULE_REWRITE",
      "signal_authorized": false,
      "trade_instruction_authorized": false,
      "broker_execution_authorized": false,
      "action_surface_authorized": false,
      "auto_learning_authorized": false,
      "rule_rewrite_authorized": false,
      "forbidden_interpretation": "Research-only shadow candidate. Do not read as buy/sell/entry/stop/target/profitability/tradability/broker execution.",
      "shadow_ledger_state": "SHADOW_REGISTERED_PENDING_OBSERVATION",
      "first_seen_utc": "2026-07-10T16:07:27Z",
      "last_seen_utc": "2026-07-10T16:57:40Z",
      "seen_refresh_count": 9,
      "ledger_authority": "SIG_SHADOW_01B_LEDGER_BUILDER_v1_0|FORWARD_SHADOW_ONLY|NOT_SIGNAL|NO_BUY_SELL|NO_ENTRY_STOP_TARGET|NO_POSITION_SIZE|NO_BROKER_EXECUTION"
    },
    {
      "candidate_id": "SCUSHADOW_704bb5bc5f5e5dfe2b9f94",
      "candidate_version": "SHADOW_CANDIDATE_UNIVERSE_01_INTAKE_v1_0",
      "candidate_state": "SHADOW_UNIVERSE_ACTIVE_PENDING_OBSERVATION_NOT_SIGNAL",
      "candidate_contract_id": "SCU01_H1_COUNTER_HTF_RECLAIM_CONTRACT_v1_0",
      "setup_cluster_id": "SCU01_CLUSTER_H1_COUNTER_HTF_RECLAIM",
      "source_memory_ids": [],
      "source_candidate_id": "SCU01_XAUUSD_H1_COUNTER_H4_BULLISH_RECLAIM_LONG_v1_0",
      "source_shadow_event_id": "SCU_EVT_df7e8e059e7328eb05be4a79",
      "source_candidate_family": "H1_COUNTER_HTF_RECLAIM",
      "source_type": "SHADOW_CANDIDATE_UNIVERSE_01_RESEARCH_ONLY",
      "instrument": "XAUUSD",
      "timeframe": "H1",
      "directional_bias": "LONG_BIAS",
      "created_utc": "2026-07-10T20:57:35Z",
      "trigger_bar_open_ts_utc": "2026-07-10T19:00:00Z",
      "valid_until_utc": "2026-07-11T03:00:00Z",
      "shadow_horizons": [
        "H1+1",
        "H1+2",
        "H1+4",
        "H1+8"
      ],
      "observation_reference_price": 4108.40211,
      "observation_reference_price_policy": "closed H1 context h1_close; observation-only, not entry",
      "source_payload_created_utc": "2026-07-10T20:57:16Z",
      "source_payload_version": "SIG_BRAIN4_RUNTIME_PAYLOAD_v1_4_EVENT_LIFECYCLE_OPS21",
      "quality_band_not_probability": "PRE_REGISTERED_SHADOW_ONLY_NO_EDGE_CLAIM",
      "source_evidence": [
        {
          "source_candidate_id": "SCU01_XAUUSD_H1_COUNTER_H4_BULLISH_RECLAIM_LONG_v1_0",
          "candidate_family": "H1_COUNTER_HTF_RECLAIM",
          "evaluation_status": "SHADOW_CANDIDATE_ACTIVE",
          "score_not_probability": 43,
          "passed_clause_count": 4,
          "total_clause_count": 4,
          "evidence_grade": "NO_EDGE_CLAIM_FORWARD_OBSERVATION_ONLY"
        }
      ],
      "latest_context_excerpt": {
        "instrument": "XAUUSD",
        "timeframe": "H1",
        "latest_bar_open_ts_utc": "2026-07-10T19:00:00Z",
        "latest_h1_bar_open_ts_utc": "2026-07-10T19:00:00Z",
        "session_bucket": "NEW_YORK",
        "h1_bar_direction": "BULLISH",
        "d1_trend_state": "UP",
        "h4_trend_state": "DOWN",
        "is_first_h1_bar_of_session": false,
        "last4_h1_contraction_flag": true,
        "current_h1_expansion_flag": false,
        "asian_high_breakout_continuation_by_closed_h1": null,
        "asian_high_swept_and_reclaimed_by_closed_h1": null,
        "weekly_open_reclaim_short_state": "NONE",
        "h1_close": 4108.40211,
        "data_sufficiency_status": "OK",
        "context_builder_status": "DERIVED_FROM_READ_ONLY_CLOSED_H1_H4_D1_BARS_OPS20"
      },
      "authority": "SHADOW_CANDIDATE_UNIVERSE_01|RESEARCH_SHADOW_ONLY|NOT_SIGNAL|NO_BUY_SELL|NO_ENTRY_STOP_TARGET|NO_POSITION_SIZE|NO_BROKER_EXECUTION|NO_AUTO_LEARNING|NO_RULE_REWRITE",
      "signal_authorized": false,
      "trade_instruction_authorized": false,
      "broker_execution_authorized": false,
      "action_surface_authorized": false,
      "auto_learning_authorized": false,
      "rule_rewrite_authorized": false,
      "forbidden_interpretation": "Research-only shadow candidate. Do not read as buy/sell/entry/stop/target/profitability/tradability/broker execution.",
      "shadow_ledger_state": "SHADOW_REGISTERED_PENDING_OBSERVATION",
      "first_seen_utc": "2026-07-10T20:07:41Z",
      "last_seen_utc": "2026-07-10T20:57:35Z",
      "seen_refresh_count": 13,
      "ledger_authority": "SIG_SHADOW_01B_LEDGER_BUILDER_v1_0|FORWARD_SHADOW_ONLY|NOT_SIGNAL|NO_BUY_SELL|NO_ENTRY_STOP_TARGET|NO_POSITION_SIZE|NO_BROKER_EXECUTION"
    },
    {
      "candidate_id": "SCUSHADOW_93887499f02b0a1d8ca60e",
      "candidate_version": "SHADOW_CANDIDATE_UNIVERSE_01_INTAKE_v1_0",
      "candidate_state": "SHADOW_UNIVERSE_ACTIVE_PENDING_OBSERVATION_NOT_SIGNAL",
      "candidate_contract_id": "SCU01_H1_COUNTER_HTF_RECLAIM_CONTRACT_v1_0",
      "setup_cluster_id": "SCU01_CLUSTER_H1_COUNTER_HTF_RECLAIM",
      "source_memory_ids": [],
      "source_candidate_id": "SCU01_XAUUSD_H1_COUNTER_H4_BULLISH_RECLAIM_LONG_v1_0",
      "source_shadow_event_id": "SCU_EVT_67feddded6960f55e9cb5104",
      "source_candidate_family": "H1_COUNTER_HTF_RECLAIM",
      "source_type": "SHADOW_CANDIDATE_UNIVERSE_01_RESEARCH_ONLY",
      "instrument": "XAUUSD",
      "timeframe": "H1",
      "directional_bias": "LONG_BIAS",
      "created_utc": "2026-07-10T21:57:32Z",
      "trigger_bar_open_ts_utc": "2026-07-10T20:00:00Z",
      "valid_until_utc": "2026-07-11T04:00:00Z",
      "shadow_horizons": [
        "H1+1",
        "H1+2",
        "H1+4",
        "H1+8"
      ],
      "observation_reference_price": 4119.32483,
      "observation_reference_price_policy": "closed H1 context h1_close; observation-only, not entry",
      "source_payload_created_utc": "2026-07-10T21:57:16Z",
      "source_payload_version": "SIG_BRAIN4_RUNTIME_PAYLOAD_v1_4_EVENT_LIFECYCLE_OPS21",
      "quality_band_not_probability": "PRE_REGISTERED_SHADOW_ONLY_NO_EDGE_CLAIM",
      "source_evidence": [
        {
          "source_candidate_id": "SCU01_XAUUSD_H1_COUNTER_H4_BULLISH_RECLAIM_LONG_v1_0",
          "candidate_family": "H1_COUNTER_HTF_RECLAIM",
          "evaluation_status": "SHADOW_CANDIDATE_ACTIVE",
          "score_not_probability": 43,
          "passed_clause_count": 4,
          "total_clause_count": 4,
          "evidence_grade": "NO_EDGE_CLAIM_FORWARD_OBSERVATION_ONLY"
        }
      ],
      "latest_context_excerpt": {
        "instrument": "XAUUSD",
        "timeframe": "H1",
        "latest_bar_open_ts_utc": "2026-07-10T20:00:00Z",
        "latest_h1_bar_open_ts_utc": "2026-07-10T20:00:00Z",
        "session_bucket": "NEW_YORK",
        "h1_bar_direction": "BULLISH",
        "d1_trend_state": "UP",
        "h4_trend_state": "DOWN",
        "is_first_h1_bar_of_session": false,
        "last4_h1_contraction_flag": true,
        "current_h1_expansion_flag": false,
        "asian_high_breakout_continuation_by_closed_h1": null,
        "asian_high_swept_and_reclaimed_by_closed_h1": null,
        "weekly_open_reclaim_short_state": "NONE",
        "h1_close": 4119.32483,
        "data_sufficiency_status": "OK",
        "context_builder_status": "DERIVED_FROM_READ_ONLY_CLOSED_H1_H4_D1_BARS_OPS20"
      },
      "authority": "SHADOW_CANDIDATE_UNIVERSE_01|RESEARCH_SHADOW_ONLY|NOT_SIGNAL|NO_BUY_SELL|NO_ENTRY_STOP_TARGET|NO_POSITION_SIZE|NO_BROKER_EXECUTION|NO_AUTO_LEARNING|NO_RULE_REWRITE",
      "signal_authorized": false,
      "trade_instruction_authorized": false,
      "broker_execution_authorized": false,
      "action_surface_authorized": false,
      "auto_learning_authorized": false,
      "rule_rewrite_authorized": false,
      "forbidden_interpretation": "Research-only shadow candidate. Do not read as buy/sell/entry/stop/target/profitability/tradability/broker execution.",
      "shadow_ledger_state": "SHADOW_REGISTERED_PENDING_OBSERVATION",
      "first_seen_utc": "2026-07-10T21:07:29Z",
      "last_seen_utc": "2026-07-10T21:57:32Z",
      "seen_refresh_count": 13,
      "ledger_authority": "SIG_SHADOW_01B_LEDGER_BUILDER_v1_0|FORWARD_SHADOW_ONLY|NOT_SIGNAL|NO_BUY_SELL|NO_ENTRY_STOP_TARGET|NO_POSITION_SIZE|NO_BROKER_EXECUTION"
    },
    {
      "candidate_id": "SCUSHADOW_ed2d8698c9f13eef12310e",
      "candidate_version": "SHADOW_CANDIDATE_UNIVERSE_01_INTAKE_v1_0",
      "candidate_state": "SHADOW_UNIVERSE_ACTIVE_PENDING_OBSERVATION_NOT_SIGNAL",
      "candidate_contract_id": "SCU01_H1_COUNTER_HTF_REJECTION_CONTRACT_v1_0",
      "setup_cluster_id": "SCU01_CLUSTER_H1_COUNTER_HTF_REJECTION",
      "source_memory_ids": [],
      "source_candidate_id": "SCU01_USDJPY_H1_COUNTER_H4_BEARISH_REJECTION_SHORT_v1_0",
      "source_shadow_event_id": "SCU_EVT_231b531304c9f0d16890c96a",
      "source_candidate_family": "H1_COUNTER_HTF_REJECTION",
      "source_type": "SHADOW_CANDIDATE_UNIVERSE_01_RESEARCH_ONLY",
      "instrument": "USDJPY",
      "timeframe": "H1",
      "directional_bias": "SHORT_BIAS",
      "created_utc": "2026-07-10T21:57:32Z",
      "trigger_bar_open_ts_utc": "2026-07-10T20:00:00Z",
      "valid_until_utc": "2026-07-11T04:00:00Z",
      "shadow_horizons": [
        "H1+1",
        "H1+2",
        "H1+4",
        "H1+8"
      ],
      "observation_reference_price": 161.69838,
      "observation_reference_price_policy": "closed H1 context h1_close; observation-only, not entry",
      "source_payload_created_utc": "2026-07-10T21:57:16Z",
      "source_payload_version": "SIG_BRAIN4_RUNTIME_PAYLOAD_v1_4_EVENT_LIFECYCLE_OPS21",
      "quality_band_not_probability": "PRE_REGISTERED_SHADOW_ONLY_NO_EDGE_CLAIM",
      "source_evidence": [
        {
          "source_candidate_id": "SCU01_USDJPY_H1_COUNTER_H4_BEARISH_REJECTION_SHORT_v1_0",
          "candidate_family": "H1_COUNTER_HTF_REJECTION",
          "evaluation_status": "SHADOW_CANDIDATE_ACTIVE",
          "score_not_probability": 43,
          "passed_clause_count": 4,
          "total_clause_count": 4,
          "evidence_grade": "NO_EDGE_CLAIM_FORWARD_OBSERVATION_ONLY"
        }
      ],
      "latest_context_excerpt": {
        "instrument": "USDJPY",
        "timeframe": "H1",
        "latest_bar_open_ts_utc": "2026-07-10T20:00:00Z",
        "latest_h1_bar_open_ts_utc": "2026-07-10T20:00:00Z",
        "session_bucket": "NEW_YORK",
        "h1_bar_direction": "BEARISH",
        "d1_trend_state": "FLAT",
        "h4_trend_state": "UP",
        "is_first_h1_bar_of_session": false,
        "last4_h1_contraction_flag": true,
        "current_h1_expansion_flag": false,
        "asian_high_breakout_continuation_by_closed_h1": null,
        "asian_high_swept_and_reclaimed_by_closed_h1": null,
        "weekly_open_reclaim_short_state": "NONE",
        "h1_close": 161.69838,
        "data_sufficiency_status": "OK",
        "context_builder_status": "DERIVED_FROM_READ_ONLY_CLOSED_H1_H4_D1_BARS_OPS20"
      },
      "authority": "SHADOW_CANDIDATE_UNIVERSE_01|RESEARCH_SHADOW_ONLY|NOT_SIGNAL|NO_BUY_SELL|NO_ENTRY_STOP_TARGET|NO_POSITION_SIZE|NO_BROKER_EXECUTION|NO_AUTO_LEARNING|NO_RULE_REWRITE",
      "signal_authorized": false,
      "trade_instruction_authorized": false,
      "broker_execution_authorized": false,
      "action_surface_authorized": false,
      "auto_learning_authorized": false,
      "rule_rewrite_authorized": false,
      "forbidden_interpretation": "Research-only shadow candidate. Do not read as buy/sell/entry/stop/target/profitability/tradability/broker execution.",
      "shadow_ledger_state": "SHADOW_REGISTERED_PENDING_OBSERVATION",
      "first_seen_utc": "2026-07-10T21:07:29Z",
      "last_seen_utc": "2026-07-10T21:57:32Z",
      "seen_refresh_count": 13,
      "ledger_authority": "SIG_SHADOW_01B_LEDGER_BUILDER_v1_0|FORWARD_SHADOW_ONLY|NOT_SIGNAL|NO_BUY_SELL|NO_ENTRY_STOP_TARGET|NO_POSITION_SIZE|NO_BROKER_EXECUTION"
    }
  ],
  "signal_authorized": false,
  "trade_instruction_authorized": false,
  "broker_execution_authorized": false,
  "action_surface_authorized": false,
  "plain_language_fa": "این فقط دفتر ثبت و مشاهدهٔ shadow است؛ سیگنال، ورود/خروج یا اجرای معامله نیست.",
  "plain_language_en": "This is a forward-shadow logging and observation layer only; not a signal, entry/exit, or execution layer."
}