{
  "payload_version": "SHADOW_OPS_01_PIPELINE_HEALTH_v1_0",
  "created_utc": "2026-07-17T06:06:51Z",
  "authority": "SHADOW_OPS_01|DIAG_ELIG_LEDGER_HEALTH_REVIEW|NOT_SIGNAL|NO_BUY_SELL|NO_ENTRY_STOP_TARGET|NO_POSITION_SIZE|NO_BROKER_EXECUTION|NO_AUTO_LEARNING|NO_RULE_REWRITE",
  "health_status": "PASS",
  "failures": [],
  "warnings": [],
  "freshness_minutes": {
    "refresh_status": 0.3,
    "brain4_payload": 0.33,
    "candidate_payload": 0.3,
    "shadow_panel_status": 0.28
  },
  "source_timestamps": {
    "refresh_created_utc": "2026-07-17T06:06:33Z",
    "brain4_created_utc": "2026-07-17T06:06:31Z",
    "candidate_created_utc": "2026-07-17T06:06:33Z",
    "shadow_panel_status_created_utc": "2026-07-17T06:06:34Z"
  },
  "boundary": {
    "signal_authorized": false,
    "trade_instruction_authorized": false,
    "broker_execution_authorized": false,
    "auto_learning_authorized": false,
    "rule_rewrite_authorized": false
  }
}