{
  "program": "PRV1-01",
  "artifact": "mtf_context_summary_v1",
  "created_at_utc": "2026-05-04T10:40:45Z",
  "source_artifact": "MTF01_Final_Delivery_Pack/context_depth_summary.json",
  "records": [
    {
      "instrument": "XAUUSD",
      "available_timeframes": [
        "M5",
        "M15",
        "H1",
        "D1"
      ],
      "missing_or_failed_timeframes": [],
      "bar_counts": {
        "M5": 49,
        "M15": 49,
        "H1": 49,
        "D1": 29
      },
      "core_m5_m15_h1_available": true,
      "d1_available": true,
      "context_depth_status": "full_requested_m5_m15_h1_d1_context_available_with_caveats",
      "latest_bar_open_by_timeframe": {
        "M5": "2026-05-02T13:55:00Z",
        "M15": "2026-05-02T13:45:00Z",
        "H1": "2026-05-02T13:00:00Z",
        "D1": "2026-05-01T00:00:00Z"
      },
      "session_event_status": "source_missing_not_assessed",
      "source_authority_status": "read_only_provider_context_only"
    },
    {
      "instrument": "EURUSD",
      "available_timeframes": [
        "M5",
        "M15",
        "H1",
        "D1"
      ],
      "missing_or_failed_timeframes": [],
      "bar_counts": {
        "M5": 49,
        "M15": 49,
        "H1": 49,
        "D1": 29
      },
      "core_m5_m15_h1_available": true,
      "d1_available": true,
      "context_depth_status": "full_requested_m5_m15_h1_d1_context_available_with_caveats",
      "latest_bar_open_by_timeframe": {
        "M5": "2026-05-02T14:15:00Z",
        "M15": "2026-05-02T14:00:00Z",
        "H1": "2026-05-02T13:00:00Z",
        "D1": "2026-05-01T00:00:00Z"
      },
      "session_event_status": "source_missing_not_assessed",
      "source_authority_status": "read_only_provider_context_only"
    },
    {
      "instrument": "USDJPY",
      "available_timeframes": [
        "M5",
        "M15",
        "H1",
        "D1"
      ],
      "missing_or_failed_timeframes": [],
      "bar_counts": {
        "M5": 49,
        "M15": 49,
        "H1": 49,
        "D1": 29
      },
      "core_m5_m15_h1_available": true,
      "d1_available": true,
      "context_depth_status": "full_requested_m5_m15_h1_d1_context_available_with_caveats",
      "latest_bar_open_by_timeframe": {
        "M5": "2026-05-02T14:00:00Z",
        "M15": "2026-05-02T13:45:00Z",
        "H1": "2026-05-02T13:00:00Z",
        "D1": "2026-05-01T00:00:00Z"
      },
      "session_event_status": "source_missing_not_assessed",
      "source_authority_status": "read_only_provider_context_only"
    }
  ],
  "coverage": {
    "active_v1_instruments": [
      "XAUUSD",
      "EURUSD",
      "USDJPY"
    ],
    "all_three_active_instruments_have_m5_m15_h1_d1_in_mtf01": true,
    "spx_nq_handling": "removed_from_active_v1_scope_not_shown_as_blocked_panel_noise"
  },
  "non_authority_statement": "Context depth is not candidate, signal, setup, or trading readiness.",
  "feed_plan_caveat": "MTF context can show M5 for XAUUSD, but RSP cache/scheduler feed plan has only 11 surfaces and does not include XAUUSD M5."
}
