{
  "program": "SIG-E-SHADOW-OBSREPORT1",
  "created_utc": "2026-07-05T19:27:30Z",
  "report_status": "OK_OBSERVATION_REPORT_READY",
  "portfolio_status": "NO_ACTIVE_SHADOW_MATCH",
  "portfolio_summary": {
    "portfolio_status": "NO_ACTIVE_SHADOW_MATCH",
    "detector_count": 4,
    "detector_status_counts": {
      "SESSION_NOT_MATCHED": 4
    },
    "classification_counts": {
      "PRIMARY_SHADOW_OBSERVATION": 2,
      "CAVEATED_OBSERVATION_ONLY": 1,
      "DIAGNOSTIC_SHADOW_OBSERVATION": 1
    },
    "active_shadow_match_count": 0,
    "active_primary_shadow_match_count": 0,
    "active_caveated_shadow_match_count": 0,
    "data_or_field_attention_count": 0,
    "total_refresh_records": 25950,
    "total_near_misses": 8004,
    "total_shadow_events": 24,
    "total_pending_shadow_events": 24,
    "total_closed_shadow_events": 0,
    "portfolio_outcome_counts": {},
    "lanes_requiring_attention": [
      {
        "lane_id": "SIGE_SD1_USDJPY_LONDON_LONG_H1_M15",
        "flags": [
          "NO_ACTION_NORMAL_NON_MATCH"
        ],
        "status": "SESSION_NOT_MATCHED"
      },
      {
        "lane_id": "SIGE_SD2_USDJPY_ASIA_SHORT_H1_M15_CAVEATED",
        "flags": [
          "NO_ACTION_NORMAL_NON_MATCH"
        ],
        "status": "SESSION_NOT_MATCHED"
      },
      {
        "lane_id": "SIGE_SD3_EURUSD_LONDON_PDLOW_TRAP_LONG_H1_M15",
        "flags": [
          "NO_ACTION_NORMAL_NON_MATCH"
        ],
        "status": "SESSION_NOT_MATCHED"
      },
      {
        "lane_id": "SIGE_SD1B_USDJPY_OVERLAP_LONG_DIAGNOSTIC_H1_M15",
        "flags": [
          "NO_ACTION_NORMAL_NON_MATCH"
        ],
        "status": "SESSION_NOT_MATCHED"
      }
    ]
  },
  "missing_state_files": [],
  "summary": {
    "lane_count": 4,
    "total_refresh_records_last_24h": 568,
    "total_refresh_records_last_7d": 4160,
    "total_shadow_events_all_time": 65,
    "active_shadow_match_count": 0,
    "data_or_field_attention_count": 0
  },
  "lanes": [
    {
      "state_file": "state/sig_e_shadow_detector_observation/usdjpy_london_long_obsledger_v1.json",
      "detector_id": "SIG_E_SHADOW_DETECTOR_USDJPY_LONDON_LONG_H1_M15_v1_0",
      "source_spec_id": "SIG_E_RUNTIME_SPEC_USDJPY_LONDON_LONG_H1_M15_v1_0",
      "display_name": "USDJPY London Long H1+M15",
      "refresh_count_total": 6499,
      "near_miss_count_total": 1326,
      "shadow_event_count_total": 24,
      "pending_shadow_event_count": 24,
      "closed_shadow_event_count": 0,
      "outcome_counts_total": {},
      "last_updated_utc": "2026-07-05T19:27:28Z",
      "windows": {
        "last_24h": {
          "record_count": 142,
          "status_counts": {
            "SESSION_NOT_MATCHED": 112,
            "REGIME_NOT_MATCHED": 12,
            "SETUP_NOT_FORMED": 18
          },
          "top_reasons": {
            "session_not_london": 112,
            "previous_h1_bar_did_not_match_lower_rejection_expansion_setup": 18,
            "d1_h4_alignment_not_matched": 12
          },
          "shadow_match_count": 0,
          "near_miss_or_progress_count": 30,
          "last_record": {
            "observation_run_id": "GH_28752198940_1",
            "record_id": "GH_28752198940_1|SIGE_SD1_USDJPY_20260705T192728Z",
            "detector_id": "SIG_E_SHADOW_DETECTOR_USDJPY_LONDON_LONG_H1_M15_v1_0",
            "source_spec_id": "SIG_E_RUNTIME_SPEC_USDJPY_LONDON_LONG_H1_M15_v1_0",
            "detector_run_id": "SIGE_SD1_USDJPY_20260705T192728Z",
            "created_utc": "2026-07-05T19:27:28Z",
            "detector_created_utc": "2026-07-05T19:27:28Z",
            "detector_status": "SESSION_NOT_MATCHED",
            "status_reason": "session_not_london",
            "is_shadow_match": false,
            "instrument": "USDJPY",
            "direction": "LONG",
            "session_bucket": "NEW_YORK",
            "d1_trend_state": "NEUTRAL",
            "h4_trend_state": "UP",
            "htf_alignment": "H4_H1_CONFLICT",
            "volatility_state_or_d1_vol_bucket": "NORMAL",
            "range_state": "EXPANSION",
            "tradeability_context": "REGIME_MIXED",
            "h1_bar_open_ts_utc": "2026-07-05T18:00:00Z",
            "m15_bar_open_ts_utc": "2026-07-05T19:00:00Z",
            "setup_h1_open_ts_utc": null,
            "trigger_h1_open_ts_utc": null,
            "m15_confirm_ts_utc": null,
            "shadow_event_id": null
          }
        },
        "last_7d": {
          "record_count": 1040,
          "status_counts": {
            "SESSION_NOT_MATCHED": 826,
            "SETUP_NOT_FORMED": 121,
            "H1_TRIGGER_WAIT": 5,
            "H1_TRIGGER_NOT_CONFIRMED": 5,
            "SHADOW_MATCH_CONFIRMED": 19,
            "REGIME_NOT_MATCHED": 64
          },
          "top_reasons": {
            "session_not_london": 826,
            "previous_h1_bar_did_not_match_lower_rejection_expansion_setup": 121,
            "d1_h4_alignment_not_matched": 64,
            "regime_setup_h1_trigger_m15_trigger_all_confirmed": 19,
            "latest_h1_bar_forms_setup_waiting_for_next_h1_close": 5,
            "next_h1_bar_did_not_confirm_long_direction": 5
          },
          "shadow_match_count": 19,
          "near_miss_or_progress_count": 214,
          "last_record": {
            "observation_run_id": "GH_28752198940_1",
            "record_id": "GH_28752198940_1|SIGE_SD1_USDJPY_20260705T192728Z",
            "detector_id": "SIG_E_SHADOW_DETECTOR_USDJPY_LONDON_LONG_H1_M15_v1_0",
            "source_spec_id": "SIG_E_RUNTIME_SPEC_USDJPY_LONDON_LONG_H1_M15_v1_0",
            "detector_run_id": "SIGE_SD1_USDJPY_20260705T192728Z",
            "created_utc": "2026-07-05T19:27:28Z",
            "detector_created_utc": "2026-07-05T19:27:28Z",
            "detector_status": "SESSION_NOT_MATCHED",
            "status_reason": "session_not_london",
            "is_shadow_match": false,
            "instrument": "USDJPY",
            "direction": "LONG",
            "session_bucket": "NEW_YORK",
            "d1_trend_state": "NEUTRAL",
            "h4_trend_state": "UP",
            "htf_alignment": "H4_H1_CONFLICT",
            "volatility_state_or_d1_vol_bucket": "NORMAL",
            "range_state": "EXPANSION",
            "tradeability_context": "REGIME_MIXED",
            "h1_bar_open_ts_utc": "2026-07-05T18:00:00Z",
            "m15_bar_open_ts_utc": "2026-07-05T19:00:00Z",
            "setup_h1_open_ts_utc": null,
            "trigger_h1_open_ts_utc": null,
            "m15_confirm_ts_utc": null,
            "shadow_event_id": null
          }
        },
        "all_time": {
          "record_count": 6499,
          "status_counts": {
            "REGIME_NOT_MATCHED": 435,
            "INPUT_INSUFFICIENT": 4,
            "LIVE_OHLC_SOURCE_MISSING": 4,
            "SETUP_NOT_FORMED": 761,
            "SESSION_NOT_MATCHED": 5165,
            "H1_TRIGGER_WAIT": 27,
            "H1_TRIGGER_NOT_CONFIRMED": 40,
            "SHADOW_MATCH_CONFIRMED": 63
          },
          "top_reasons": {
            "session_not_london": 5165,
            "previous_h1_bar_did_not_match_lower_rejection_expansion_setup": 761,
            "d1_h4_alignment_not_matched": 435,
            "regime_setup_h1_trigger_m15_trigger_all_confirmed": 63,
            "next_h1_bar_did_not_confirm_long_direction": 40,
            "latest_h1_bar_forms_setup_waiting_for_next_h1_close": 27,
            "not_enough_h1_rows_for_setup_trigger_window": 4,
            "live_h1_or_m15_ohlc_source_missing_no_historical_fallback_allowed": 4
          },
          "shadow_match_count": 63,
          "near_miss_or_progress_count": 1326,
          "last_record": {
            "observation_run_id": "GH_28752198940_1",
            "record_id": "GH_28752198940_1|SIGE_SD1_USDJPY_20260705T192728Z",
            "detector_id": "SIG_E_SHADOW_DETECTOR_USDJPY_LONDON_LONG_H1_M15_v1_0",
            "source_spec_id": "SIG_E_RUNTIME_SPEC_USDJPY_LONDON_LONG_H1_M15_v1_0",
            "detector_run_id": "SIGE_SD1_USDJPY_20260705T192728Z",
            "created_utc": "2026-07-05T19:27:28Z",
            "detector_created_utc": "2026-07-05T19:27:28Z",
            "detector_status": "SESSION_NOT_MATCHED",
            "status_reason": "session_not_london",
            "is_shadow_match": false,
            "instrument": "USDJPY",
            "direction": "LONG",
            "session_bucket": "NEW_YORK",
            "d1_trend_state": "NEUTRAL",
            "h4_trend_state": "UP",
            "htf_alignment": "H4_H1_CONFLICT",
            "volatility_state_or_d1_vol_bucket": "NORMAL",
            "range_state": "EXPANSION",
            "tradeability_context": "REGIME_MIXED",
            "h1_bar_open_ts_utc": "2026-07-05T18:00:00Z",
            "m15_bar_open_ts_utc": "2026-07-05T19:00:00Z",
            "setup_h1_open_ts_utc": null,
            "trigger_h1_open_ts_utc": null,
            "m15_confirm_ts_utc": null,
            "shadow_event_id": null
          }
        }
      },
      "latest_near_miss": {
        "observation_run_id": "GH_28741528639_1",
        "record_id": "GH_28741528639_1|SIGE_SD1_USDJPY_20260705T125732Z",
        "detector_id": "SIG_E_SHADOW_DETECTOR_USDJPY_LONDON_LONG_H1_M15_v1_0",
        "source_spec_id": "SIG_E_RUNTIME_SPEC_USDJPY_LONDON_LONG_H1_M15_v1_0",
        "detector_run_id": "SIGE_SD1_USDJPY_20260705T125732Z",
        "created_utc": "2026-07-05T12:57:32Z",
        "detector_created_utc": "2026-07-05T12:57:32Z",
        "detector_status": "REGIME_NOT_MATCHED",
        "status_reason": "d1_h4_alignment_not_matched",
        "is_shadow_match": false,
        "instrument": "USDJPY",
        "direction": "LONG",
        "session_bucket": "LONDON",
        "d1_trend_state": "NEUTRAL",
        "h4_trend_state": "UP",
        "htf_alignment": "H4_H1_CONFLICT",
        "volatility_state_or_d1_vol_bucket": "NORMAL",
        "range_state": "EXPANSION_AFTER_COMPRESSION",
        "tradeability_context": "REGIME_MIXED",
        "h1_bar_open_ts_utc": "2026-07-05T11:00:00Z",
        "m15_bar_open_ts_utc": "2026-07-05T12:30:00Z",
        "setup_h1_open_ts_utc": null,
        "trigger_h1_open_ts_utc": null,
        "m15_confirm_ts_utc": null,
        "shadow_event_id": null,
        "near_miss_score": 1
      },
      "latest_shadow_event": {
        "detector_id": "SIG_E_SHADOW_DETECTOR_USDJPY_LONDON_LONG_H1_M15_v1_0",
        "source_spec_id": "SIG_E_RUNTIME_SPEC_USDJPY_LONDON_LONG_H1_M15_v1_0",
        "shadow_event_id": "SIGE_SD1_USDJPY_LONDON_LONG_20260704T120000",
        "created_utc": "2026-07-04T12:26:52Z",
        "instrument": "USDJPY",
        "direction": "LONG",
        "detector_status": "SHADOW_MATCH_CONFIRMED",
        "setup_h1_open_ts_utc": "2026-07-04T11:00:00Z",
        "trigger_h1_open_ts_utc": "2026-07-04T12:00:00Z",
        "m15_confirm_ts_utc": "2026-07-04T12:00:00Z",
        "observation_horizon_h1_bars": 16,
        "observation_end_ts_utc": "2026-07-05T04:00:00Z",
        "outcome_status": "PENDING",
        "source_paths": {
          "h1_ohlc_path": "data/live_resampled/USDJPY_H1_from_M5.csv.gz",
          "m15_ohlc_path": "data/live_resampled/USDJPY_M15_from_M5.csv.gz",
          "live_source_policy": "live_only_no_data_canonical_fallback"
        },
        "authority": {
          "signal_authorized": false,
          "trade_proposal_authorized": false,
          "entry_stop_target_authorized": false,
          "risk_sizing_authorized": false,
          "broker_execution_authorized": false,
          "auto_execution_authorized": false
        },
        "boundary": [
          "OBSERVATION_LEDGER_ONLY",
          "SHADOW_RESEARCH_ONLY",
          "NOT_SIGNAL",
          "NO_TRADE_PROPOSAL",
          "NO_ENTRY_STOP_TARGET",
          "NO_RISK_OR_POSITION_SIZING",
          "NO_BROKER_EXECUTION",
          "NO_AUTO_EXECUTION",
          "NO_MEMORY_PROMOTION",
          "NO_RULE_REWRITE"
        ]
      },
      "latest_outcome": null
    },
    {
      "state_file": "state/sig_e_shadow_detector_observation/usdjpy_overlap_long_diagnostic_obsledger_v1.json",
      "detector_id": "SIG_E_SHADOW_DETECTOR1B_USDJPY_OVERLAP_LONG_DIAGNOSTIC_H1_M15_v1_0",
      "source_spec_id": "SIG_E_RUNTIME_SPEC_USDJPY_OVERLAP_LONG_DIAGNOSTIC_H1_M15_v1_0",
      "display_name": "SIG_E_SHADOW_DETECTOR1B_USDJPY_OVERLAP_LONG_DIAGNOSTIC_H1_M15_v1_0",
      "refresh_count_total": 6469,
      "near_miss_count_total": 2400,
      "shadow_event_count_total": 41,
      "pending_shadow_event_count": 41,
      "closed_shadow_event_count": 0,
      "outcome_counts_total": {},
      "last_updated_utc": "2026-07-05T19:27:29Z",
      "windows": {
        "last_24h": {
          "record_count": 142,
          "status_counts": {
            "SESSION_NOT_MATCHED": 88,
            "REGIME_NOT_MATCHED": 24,
            "SETUP_NOT_FORMED": 30
          },
          "top_reasons": {
            "session_not_london_ny_overlap": 88,
            "previous_h1_bar_did_not_match_lower_rejection_expansion_setup": 18,
            "d1_h4_alignment_not_matched": 12,
            "previous_h1_bar_did_not_match_overlap_lower_rejection_expansion_setup": 12,
            "overlap_long_diagnostic_regime_not_matched": 12
          },
          "shadow_match_count": 0,
          "near_miss_or_progress_count": 54,
          "last_record": {
            "observation_run_id": "GH_28752198940_1",
            "record_id": "GH_28752198940_1|SIGE_SD1B_USDJPY_OVERLAP_20260705T192729Z",
            "detector_id": "SIG_E_SHADOW_DETECTOR1B_USDJPY_OVERLAP_LONG_DIAGNOSTIC_H1_M15_v1_0",
            "source_spec_id": "SIG_E_RUNTIME_SPEC_USDJPY_OVERLAP_LONG_DIAGNOSTIC_H1_M15_v1_0",
            "detector_run_id": "SIGE_SD1B_USDJPY_OVERLAP_20260705T192729Z",
            "created_utc": "2026-07-05T19:27:29Z",
            "detector_created_utc": "2026-07-05T19:27:29Z",
            "detector_status": "SESSION_NOT_MATCHED",
            "status_reason": "session_not_london_ny_overlap",
            "is_shadow_match": false,
            "is_diagnostic_shadow_match": false,
            "instrument": "USDJPY",
            "direction": "LONG",
            "classification": "DIAGNOSTIC_ONLY_SHADOW_LANE_NOT_PRIMARY",
            "session_bucket": "NEW_YORK",
            "d1_trend_state": "NEUTRAL",
            "h4_trend_state": "UP",
            "htf_alignment": "H4_H1_CONFLICT",
            "volatility_state_or_d1_vol_bucket": "NORMAL",
            "range_state": "EXPANSION",
            "tradeability_context": "REGIME_MIXED",
            "h1_bar_open_ts_utc": "2026-07-05T18:00:00Z",
            "m15_bar_open_ts_utc": "2026-07-05T19:00:00Z",
            "setup_h1_open_ts_utc": null,
            "trigger_h1_open_ts_utc": null,
            "m15_confirm_ts_utc": null,
            "shadow_event_id": null
          }
        },
        "last_7d": {
          "record_count": 1040,
          "status_counts": {
            "SESSION_NOT_MATCHED": 649,
            "SETUP_NOT_FORMED": 204,
            "H1_TRIGGER_WAIT": 8,
            "H1_TRIGGER_NOT_CONFIRMED": 15,
            "DIAGNOSTIC_SHADOW_MATCH_CONFIRMED": 37,
            "REGIME_NOT_MATCHED": 127
          },
          "top_reasons": {
            "session_not_london_ny_overlap": 649,
            "previous_h1_bar_did_not_match_lower_rejection_expansion_setup": 121,
            "previous_h1_bar_did_not_match_overlap_lower_rejection_expansion_setup": 83,
            "d1_h4_alignment_not_matched": 64,
            "overlap_long_diagnostic_regime_not_matched": 63,
            "regime_setup_h1_trigger_m15_trigger_all_confirmed": 19,
            "usdjpy_overlap_lower_rejection_expansion_long_diagnostic_shadow_match_confirmed": 18,
            "next_h1_bar_did_not_confirm_bullish_overlap_followthrough": 10,
            "latest_h1_bar_forms_setup_waiting_for_next_h1_close": 5,
            "next_h1_bar_did_not_confirm_long_direction": 5
          },
          "shadow_match_count": 37,
          "near_miss_or_progress_count": 354,
          "last_record": {
            "observation_run_id": "GH_28752198940_1",
            "record_id": "GH_28752198940_1|SIGE_SD1B_USDJPY_OVERLAP_20260705T192729Z",
            "detector_id": "SIG_E_SHADOW_DETECTOR1B_USDJPY_OVERLAP_LONG_DIAGNOSTIC_H1_M15_v1_0",
            "source_spec_id": "SIG_E_RUNTIME_SPEC_USDJPY_OVERLAP_LONG_DIAGNOSTIC_H1_M15_v1_0",
            "detector_run_id": "SIGE_SD1B_USDJPY_OVERLAP_20260705T192729Z",
            "created_utc": "2026-07-05T19:27:29Z",
            "detector_created_utc": "2026-07-05T19:27:29Z",
            "detector_status": "SESSION_NOT_MATCHED",
            "status_reason": "session_not_london_ny_overlap",
            "is_shadow_match": false,
            "is_diagnostic_shadow_match": false,
            "instrument": "USDJPY",
            "direction": "LONG",
            "classification": "DIAGNOSTIC_ONLY_SHADOW_LANE_NOT_PRIMARY",
            "session_bucket": "NEW_YORK",
            "d1_trend_state": "NEUTRAL",
            "h4_trend_state": "UP",
            "htf_alignment": "H4_H1_CONFLICT",
            "volatility_state_or_d1_vol_bucket": "NORMAL",
            "range_state": "EXPANSION",
            "tradeability_context": "REGIME_MIXED",
            "h1_bar_open_ts_utc": "2026-07-05T18:00:00Z",
            "m15_bar_open_ts_utc": "2026-07-05T19:00:00Z",
            "setup_h1_open_ts_utc": null,
            "trigger_h1_open_ts_utc": null,
            "m15_confirm_ts_utc": null,
            "shadow_event_id": null
          }
        },
        "all_time": {
          "record_count": 6469,
          "status_counts": {
            "SESSION_NOT_MATCHED": 4069,
            "REGIME_NOT_MATCHED": 812,
            "SETUP_NOT_FORMED": 1338,
            "H1_TRIGGER_WAIT": 58,
            "H1_TRIGGER_NOT_CONFIRMED": 84,
            "DIAGNOSTIC_SHADOW_MATCH_CONFIRMED": 108
          },
          "top_reasons": {
            "session_not_london_ny_overlap": 4069,
            "previous_h1_bar_did_not_match_lower_rejection_expansion_setup": 755,
            "previous_h1_bar_did_not_match_overlap_lower_rejection_expansion_setup": 583,
            "d1_h4_alignment_not_matched": 433,
            "overlap_long_diagnostic_regime_not_matched": 379,
            "regime_setup_h1_trigger_m15_trigger_all_confirmed": 63,
            "usdjpy_overlap_lower_rejection_expansion_long_diagnostic_shadow_match_confirmed": 45,
            "next_h1_bar_did_not_confirm_bullish_overlap_followthrough": 44,
            "next_h1_bar_did_not_confirm_long_direction": 40,
            "latest_h1_bar_forms_overlap_lower_rejection_expansion_setup_waiting_for_next_h1_close": 31
          },
          "shadow_match_count": 108,
          "near_miss_or_progress_count": 2292,
          "last_record": {
            "observation_run_id": "GH_28752198940_1",
            "record_id": "GH_28752198940_1|SIGE_SD1B_USDJPY_OVERLAP_20260705T192729Z",
            "detector_id": "SIG_E_SHADOW_DETECTOR1B_USDJPY_OVERLAP_LONG_DIAGNOSTIC_H1_M15_v1_0",
            "source_spec_id": "SIG_E_RUNTIME_SPEC_USDJPY_OVERLAP_LONG_DIAGNOSTIC_H1_M15_v1_0",
            "detector_run_id": "SIGE_SD1B_USDJPY_OVERLAP_20260705T192729Z",
            "created_utc": "2026-07-05T19:27:29Z",
            "detector_created_utc": "2026-07-05T19:27:29Z",
            "detector_status": "SESSION_NOT_MATCHED",
            "status_reason": "session_not_london_ny_overlap",
            "is_shadow_match": false,
            "is_diagnostic_shadow_match": false,
            "instrument": "USDJPY",
            "direction": "LONG",
            "classification": "DIAGNOSTIC_ONLY_SHADOW_LANE_NOT_PRIMARY",
            "session_bucket": "NEW_YORK",
            "d1_trend_state": "NEUTRAL",
            "h4_trend_state": "UP",
            "htf_alignment": "H4_H1_CONFLICT",
            "volatility_state_or_d1_vol_bucket": "NORMAL",
            "range_state": "EXPANSION",
            "tradeability_context": "REGIME_MIXED",
            "h1_bar_open_ts_utc": "2026-07-05T18:00:00Z",
            "m15_bar_open_ts_utc": "2026-07-05T19:00:00Z",
            "setup_h1_open_ts_utc": null,
            "trigger_h1_open_ts_utc": null,
            "m15_confirm_ts_utc": null,
            "shadow_event_id": null
          }
        }
      },
      "latest_near_miss": {
        "observation_run_id": "GH_28748119199_1",
        "record_id": "GH_28748119199_1|SIGE_SD1B_USDJPY_OVERLAP_20260705T165738Z",
        "detector_id": "SIG_E_SHADOW_DETECTOR1B_USDJPY_OVERLAP_LONG_DIAGNOSTIC_H1_M15_v1_0",
        "source_spec_id": "SIG_E_RUNTIME_SPEC_USDJPY_OVERLAP_LONG_DIAGNOSTIC_H1_M15_v1_0",
        "detector_run_id": "SIGE_SD1B_USDJPY_OVERLAP_20260705T165738Z",
        "created_utc": "2026-07-05T16:57:38Z",
        "detector_created_utc": "2026-07-05T16:57:38Z",
        "detector_status": "REGIME_NOT_MATCHED",
        "status_reason": "overlap_long_diagnostic_regime_not_matched",
        "is_shadow_match": false,
        "is_diagnostic_shadow_match": false,
        "instrument": "USDJPY",
        "direction": "LONG",
        "classification": "DIAGNOSTIC_ONLY_SHADOW_LANE_NOT_PRIMARY",
        "session_bucket": "LONDON_NY_OVERLAP",
        "d1_trend_state": "NEUTRAL",
        "h4_trend_state": "UP",
        "htf_alignment": "H4_H1_CONFLICT",
        "volatility_state_or_d1_vol_bucket": "NORMAL",
        "range_state": "EXPANSION",
        "tradeability_context": "REGIME_MIXED",
        "h1_bar_open_ts_utc": "2026-07-05T15:00:00Z",
        "m15_bar_open_ts_utc": "2026-07-05T16:30:00Z",
        "setup_h1_open_ts_utc": null,
        "trigger_h1_open_ts_utc": null,
        "m15_confirm_ts_utc": null,
        "shadow_event_id": null,
        "near_miss_score": 1
      },
      "latest_shadow_event": {
        "detector_id": "SIG_E_SHADOW_DETECTOR1B_USDJPY_OVERLAP_LONG_DIAGNOSTIC_H1_M15_v1_0",
        "source_spec_id": "SIG_E_RUNTIME_SPEC_USDJPY_OVERLAP_LONG_DIAGNOSTIC_H1_M15_v1_0",
        "shadow_event_id": "SIGE_SD1B_USDJPY_OVERLAP_LONG_DIAGNOSTIC_20260704T160000",
        "created_utc": "2026-07-04T16:46:46Z",
        "instrument": "USDJPY",
        "direction": "LONG",
        "classification": "DIAGNOSTIC_ONLY_SHADOW_LANE_NOT_PRIMARY",
        "detector_status": "DIAGNOSTIC_SHADOW_MATCH_CONFIRMED",
        "setup_h1_open_ts_utc": "2026-07-04T15:00:00Z",
        "trigger_h1_open_ts_utc": "2026-07-04T16:00:00Z",
        "observation_horizon_h1_bars": 12,
        "outcome_status": "PENDING",
        "authority": {
          "signal_authorized": false,
          "trade_proposal_authorized": false,
          "entry_stop_target_authorized": false,
          "risk_sizing_authorized": false,
          "broker_execution_authorized": false,
          "auto_execution_authorized": false,
          "primary_lane_authorized": false,
          "lane_rule_change_authorized": false
        },
        "boundary": [
          "OBSERVATION_LEDGER_ONLY",
          "DIAGNOSTIC_ONLY_LANE",
          "OVERLAP_VARIANT_RESEARCH_ONLY",
          "DOES_NOT_CHANGE_LANE1",
          "SHADOW_RESEARCH_ONLY",
          "NOT_SIGNAL",
          "NO_TRADE_PROPOSAL",
          "NO_ENTRY_STOP_TARGET",
          "NO_RISK_OR_POSITION_SIZING",
          "NO_BROKER_EXECUTION",
          "NO_AUTO_EXECUTION",
          "NO_MEMORY_PROMOTION",
          "NO_RULE_REWRITE"
        ]
      },
      "latest_outcome": null
    },
    {
      "state_file": "state/sig_e_shadow_detector_observation/usdjpy_asia_short_obsledger_v1.json",
      "detector_id": "SIG_E_SHADOW_DETECTOR_USDJPY_ASIA_SHORT_H1_M15_CAVEATED_v1_0",
      "source_spec_id": "SIG_E_RUNTIME_SPEC_USDJPY_ASIA_SHORT_H1_M15_CAVEATED_v1_0",
      "display_name": "USDJPY Asia Short H1+M15 Caveated",
      "refresh_count_total": 6499,
      "near_miss_count_total": 1859,
      "shadow_event_count_total": 0,
      "pending_shadow_event_count": 0,
      "closed_shadow_event_count": 0,
      "outcome_counts_total": {},
      "last_updated_utc": "2026-07-05T19:27:28Z",
      "windows": {
        "last_24h": {
          "record_count": 142,
          "status_counts": {
            "SESSION_NOT_MATCHED": 101,
            "REGIME_NOT_MATCHED": 41
          },
          "top_reasons": {
            "session_not_asia": 101,
            "d1_h4_down_alignment_not_matched": 41
          },
          "shadow_match_count": 0,
          "near_miss_or_progress_count": 41,
          "last_record": {
            "observation_run_id": "GH_28752198940_1",
            "record_id": "GH_28752198940_1|SIGE_SD2_USDJPY_20260705T192728Z",
            "detector_id": "SIG_E_SHADOW_DETECTOR_USDJPY_ASIA_SHORT_H1_M15_CAVEATED_v1_0",
            "source_spec_id": "SIG_E_RUNTIME_SPEC_USDJPY_ASIA_SHORT_H1_M15_CAVEATED_v1_0",
            "detector_run_id": "SIGE_SD2_USDJPY_20260705T192728Z",
            "created_utc": "2026-07-05T19:27:28Z",
            "detector_created_utc": "2026-07-05T19:27:28Z",
            "detector_status": "SESSION_NOT_MATCHED",
            "status_reason": "session_not_asia",
            "is_shadow_match": false,
            "is_caveated_observation": true,
            "instrument": "USDJPY",
            "direction": "SHORT",
            "session_bucket": "NEW_YORK",
            "d1_trend_state": "NEUTRAL",
            "h4_trend_state": "UP",
            "htf_alignment": "H4_H1_CONFLICT",
            "range_state": "EXPANSION",
            "h1_bar_open_ts_utc": "2026-07-05T18:00:00Z",
            "m15_bar_open_ts_utc": "2026-07-05T19:00:00Z",
            "setup_h1_open_ts_utc": null,
            "trigger_h1_open_ts_utc": null,
            "shadow_event_id": null
          }
        },
        "last_7d": {
          "record_count": 1040,
          "status_counts": {
            "SESSION_NOT_MATCHED": 740,
            "REGIME_NOT_MATCHED": 300
          },
          "top_reasons": {
            "session_not_asia": 740,
            "d1_h4_down_alignment_not_matched": 300
          },
          "shadow_match_count": 0,
          "near_miss_or_progress_count": 300,
          "last_record": {
            "observation_run_id": "GH_28752198940_1",
            "record_id": "GH_28752198940_1|SIGE_SD2_USDJPY_20260705T192728Z",
            "detector_id": "SIG_E_SHADOW_DETECTOR_USDJPY_ASIA_SHORT_H1_M15_CAVEATED_v1_0",
            "source_spec_id": "SIG_E_RUNTIME_SPEC_USDJPY_ASIA_SHORT_H1_M15_CAVEATED_v1_0",
            "detector_run_id": "SIGE_SD2_USDJPY_20260705T192728Z",
            "created_utc": "2026-07-05T19:27:28Z",
            "detector_created_utc": "2026-07-05T19:27:28Z",
            "detector_status": "SESSION_NOT_MATCHED",
            "status_reason": "session_not_asia",
            "is_shadow_match": false,
            "is_caveated_observation": true,
            "instrument": "USDJPY",
            "direction": "SHORT",
            "session_bucket": "NEW_YORK",
            "d1_trend_state": "NEUTRAL",
            "h4_trend_state": "UP",
            "htf_alignment": "H4_H1_CONFLICT",
            "range_state": "EXPANSION",
            "h1_bar_open_ts_utc": "2026-07-05T18:00:00Z",
            "m15_bar_open_ts_utc": "2026-07-05T19:00:00Z",
            "setup_h1_open_ts_utc": null,
            "trigger_h1_open_ts_utc": null,
            "shadow_event_id": null
          }
        },
        "all_time": {
          "record_count": 6499,
          "status_counts": {
            "SESSION_NOT_MATCHED": 4640,
            "REGIME_NOT_MATCHED": 1859
          },
          "top_reasons": {
            "session_not_asia": 4640,
            "d1_h4_down_alignment_not_matched": 1859
          },
          "shadow_match_count": 0,
          "near_miss_or_progress_count": 1859,
          "last_record": {
            "observation_run_id": "GH_28752198940_1",
            "record_id": "GH_28752198940_1|SIGE_SD2_USDJPY_20260705T192728Z",
            "detector_id": "SIG_E_SHADOW_DETECTOR_USDJPY_ASIA_SHORT_H1_M15_CAVEATED_v1_0",
            "source_spec_id": "SIG_E_RUNTIME_SPEC_USDJPY_ASIA_SHORT_H1_M15_CAVEATED_v1_0",
            "detector_run_id": "SIGE_SD2_USDJPY_20260705T192728Z",
            "created_utc": "2026-07-05T19:27:28Z",
            "detector_created_utc": "2026-07-05T19:27:28Z",
            "detector_status": "SESSION_NOT_MATCHED",
            "status_reason": "session_not_asia",
            "is_shadow_match": false,
            "is_caveated_observation": true,
            "instrument": "USDJPY",
            "direction": "SHORT",
            "session_bucket": "NEW_YORK",
            "d1_trend_state": "NEUTRAL",
            "h4_trend_state": "UP",
            "htf_alignment": "H4_H1_CONFLICT",
            "range_state": "EXPANSION",
            "h1_bar_open_ts_utc": "2026-07-05T18:00:00Z",
            "m15_bar_open_ts_utc": "2026-07-05T19:00:00Z",
            "setup_h1_open_ts_utc": null,
            "trigger_h1_open_ts_utc": null,
            "shadow_event_id": null
          }
        }
      },
      "latest_near_miss": {
        "observation_run_id": "GH_28734013756_1",
        "record_id": "GH_28734013756_1|SIGE_SD2_USDJPY_20260705T075717Z",
        "detector_id": "SIG_E_SHADOW_DETECTOR_USDJPY_ASIA_SHORT_H1_M15_CAVEATED_v1_0",
        "source_spec_id": "SIG_E_RUNTIME_SPEC_USDJPY_ASIA_SHORT_H1_M15_CAVEATED_v1_0",
        "detector_run_id": "SIGE_SD2_USDJPY_20260705T075717Z",
        "created_utc": "2026-07-05T07:57:17Z",
        "detector_created_utc": "2026-07-05T07:57:17Z",
        "detector_status": "REGIME_NOT_MATCHED",
        "status_reason": "d1_h4_down_alignment_not_matched",
        "is_shadow_match": false,
        "is_caveated_observation": true,
        "instrument": "USDJPY",
        "direction": "SHORT",
        "session_bucket": "ASIA",
        "d1_trend_state": "NEUTRAL",
        "h4_trend_state": "UP",
        "htf_alignment": "H4_H1_CONFLICT",
        "range_state": "COMPRESSION",
        "h1_bar_open_ts_utc": "2026-07-05T06:00:00Z",
        "m15_bar_open_ts_utc": "2026-07-05T07:30:00Z",
        "setup_h1_open_ts_utc": null,
        "trigger_h1_open_ts_utc": null,
        "shadow_event_id": null,
        "near_miss_score": 1
      },
      "latest_shadow_event": null,
      "latest_outcome": null
    },
    {
      "state_file": "state/sig_e_shadow_detector_observation/eurusd_london_pdlow_trap_long_obsledger_v1.json",
      "detector_id": "SIG_E_SHADOW_DETECTOR_EURUSD_LONDON_PDLOW_TRAP_LONG_H1_M15_v1_0",
      "source_spec_id": "SIG_E_RUNTIME_SPEC_EURUSD_LONDON_PDLOW_TRAP_LONG_H1_M15_v1_0",
      "display_name": "EURUSD London/Overlap Prior-Day-Low Trap Long H1+M15",
      "refresh_count_total": 6483,
      "near_miss_count_total": 2419,
      "shadow_event_count_total": 0,
      "pending_shadow_event_count": 0,
      "closed_shadow_event_count": 0,
      "outcome_counts_total": {},
      "last_updated_utc": "2026-07-05T19:27:28Z",
      "windows": {
        "last_24h": {
          "record_count": 142,
          "status_counts": {
            "SESSION_NOT_MATCHED": 88,
            "REGIME_NOT_MATCHED": 54
          },
          "top_reasons": {
            "session_not_london_or_overlap": 88,
            "eurusd_long_trap_regime_not_matched": 54
          },
          "shadow_match_count": 0,
          "near_miss_or_progress_count": 54,
          "last_record": {
            "observation_run_id": "GH_28752198940_1",
            "record_id": "GH_28752198940_1|SIGE_SD3_EURUSD_20260705T192728Z",
            "detector_id": "SIG_E_SHADOW_DETECTOR_EURUSD_LONDON_PDLOW_TRAP_LONG_H1_M15_v1_0",
            "source_spec_id": "SIG_E_RUNTIME_SPEC_EURUSD_LONDON_PDLOW_TRAP_LONG_H1_M15_v1_0",
            "detector_run_id": "SIGE_SD3_EURUSD_20260705T192728Z",
            "created_utc": "2026-07-05T19:27:28Z",
            "detector_created_utc": "2026-07-05T19:27:28Z",
            "detector_status": "SESSION_NOT_MATCHED",
            "status_reason": "session_not_london_or_overlap",
            "is_shadow_match": false,
            "instrument": "EURUSD",
            "direction": "LONG",
            "session_bucket": "NEW_YORK",
            "d1_trend_state": "NEUTRAL",
            "h4_trend_state": "DOWN",
            "htf_alignment": "H4_H1_ALIGNED_DOWN",
            "volatility_state_or_d1_vol_bucket": "LOW",
            "range_state": "COMPRESSION",
            "tradeability_context": "DATA_INSUFFICIENT",
            "h1_bar_open_ts_utc": "2026-07-05T18:00:00Z",
            "m15_bar_open_ts_utc": "2026-07-05T19:00:00Z",
            "setup_h1_open_ts_utc": null,
            "trigger_h1_open_ts_utc": null,
            "m15_confirm_ts_utc": null,
            "shadow_event_id": null
          }
        },
        "last_7d": {
          "record_count": 1040,
          "status_counts": {
            "SESSION_NOT_MATCHED": 649,
            "REGIME_NOT_MATCHED": 391
          },
          "top_reasons": {
            "session_not_london_or_overlap": 649,
            "eurusd_long_trap_regime_not_matched": 391
          },
          "shadow_match_count": 0,
          "near_miss_or_progress_count": 391,
          "last_record": {
            "observation_run_id": "GH_28752198940_1",
            "record_id": "GH_28752198940_1|SIGE_SD3_EURUSD_20260705T192728Z",
            "detector_id": "SIG_E_SHADOW_DETECTOR_EURUSD_LONDON_PDLOW_TRAP_LONG_H1_M15_v1_0",
            "source_spec_id": "SIG_E_RUNTIME_SPEC_EURUSD_LONDON_PDLOW_TRAP_LONG_H1_M15_v1_0",
            "detector_run_id": "SIGE_SD3_EURUSD_20260705T192728Z",
            "created_utc": "2026-07-05T19:27:28Z",
            "detector_created_utc": "2026-07-05T19:27:28Z",
            "detector_status": "SESSION_NOT_MATCHED",
            "status_reason": "session_not_london_or_overlap",
            "is_shadow_match": false,
            "instrument": "EURUSD",
            "direction": "LONG",
            "session_bucket": "NEW_YORK",
            "d1_trend_state": "NEUTRAL",
            "h4_trend_state": "DOWN",
            "htf_alignment": "H4_H1_ALIGNED_DOWN",
            "volatility_state_or_d1_vol_bucket": "LOW",
            "range_state": "COMPRESSION",
            "tradeability_context": "DATA_INSUFFICIENT",
            "h1_bar_open_ts_utc": "2026-07-05T18:00:00Z",
            "m15_bar_open_ts_utc": "2026-07-05T19:00:00Z",
            "setup_h1_open_ts_utc": null,
            "trigger_h1_open_ts_utc": null,
            "m15_confirm_ts_utc": null,
            "shadow_event_id": null
          }
        },
        "all_time": {
          "record_count": 6483,
          "status_counts": {
            "REGIME_NOT_MATCHED": 2261,
            "SESSION_NOT_MATCHED": 4064,
            "REFERENCE_LEVEL_UNAVAILABLE": 158
          },
          "top_reasons": {
            "session_not_london_or_overlap": 4064,
            "eurusd_long_trap_regime_not_matched": 2261,
            "prior_utc_day_low_unavailable_from_live_h1": 158
          },
          "shadow_match_count": 0,
          "near_miss_or_progress_count": 2261,
          "last_record": {
            "observation_run_id": "GH_28752198940_1",
            "record_id": "GH_28752198940_1|SIGE_SD3_EURUSD_20260705T192728Z",
            "detector_id": "SIG_E_SHADOW_DETECTOR_EURUSD_LONDON_PDLOW_TRAP_LONG_H1_M15_v1_0",
            "source_spec_id": "SIG_E_RUNTIME_SPEC_EURUSD_LONDON_PDLOW_TRAP_LONG_H1_M15_v1_0",
            "detector_run_id": "SIGE_SD3_EURUSD_20260705T192728Z",
            "created_utc": "2026-07-05T19:27:28Z",
            "detector_created_utc": "2026-07-05T19:27:28Z",
            "detector_status": "SESSION_NOT_MATCHED",
            "status_reason": "session_not_london_or_overlap",
            "is_shadow_match": false,
            "instrument": "EURUSD",
            "direction": "LONG",
            "session_bucket": "NEW_YORK",
            "d1_trend_state": "NEUTRAL",
            "h4_trend_state": "DOWN",
            "htf_alignment": "H4_H1_ALIGNED_DOWN",
            "volatility_state_or_d1_vol_bucket": "LOW",
            "range_state": "COMPRESSION",
            "tradeability_context": "DATA_INSUFFICIENT",
            "h1_bar_open_ts_utc": "2026-07-05T18:00:00Z",
            "m15_bar_open_ts_utc": "2026-07-05T19:00:00Z",
            "setup_h1_open_ts_utc": null,
            "trigger_h1_open_ts_utc": null,
            "m15_confirm_ts_utc": null,
            "shadow_event_id": null
          }
        }
      },
      "latest_near_miss": {
        "observation_run_id": "GH_28748119199_1",
        "record_id": "GH_28748119199_1|SIGE_SD3_EURUSD_20260705T165738Z",
        "detector_id": "SIG_E_SHADOW_DETECTOR_EURUSD_LONDON_PDLOW_TRAP_LONG_H1_M15_v1_0",
        "source_spec_id": "SIG_E_RUNTIME_SPEC_EURUSD_LONDON_PDLOW_TRAP_LONG_H1_M15_v1_0",
        "detector_run_id": "SIGE_SD3_EURUSD_20260705T165738Z",
        "created_utc": "2026-07-05T16:57:38Z",
        "detector_created_utc": "2026-07-05T16:57:38Z",
        "detector_status": "REGIME_NOT_MATCHED",
        "status_reason": "eurusd_long_trap_regime_not_matched",
        "is_shadow_match": false,
        "instrument": "EURUSD",
        "direction": "LONG",
        "session_bucket": "LONDON_NY_OVERLAP",
        "d1_trend_state": "NEUTRAL",
        "h4_trend_state": "DOWN",
        "htf_alignment": "H4_H1_ALIGNED_DOWN",
        "volatility_state_or_d1_vol_bucket": "LOW",
        "range_state": "COMPRESSION",
        "tradeability_context": "DATA_INSUFFICIENT",
        "h1_bar_open_ts_utc": "2026-07-05T15:00:00Z",
        "m15_bar_open_ts_utc": "2026-07-05T16:30:00Z",
        "setup_h1_open_ts_utc": null,
        "trigger_h1_open_ts_utc": null,
        "m15_confirm_ts_utc": null,
        "shadow_event_id": null,
        "near_miss_score": 1
      },
      "latest_shadow_event": null,
      "latest_outcome": null
    }
  ],
  "authority": {
    "signal_authorized": false,
    "trade_proposal_authorized": false,
    "entry_stop_target_authorized": false,
    "risk_sizing_authorized": false,
    "broker_execution_authorized": false,
    "auto_execution_authorized": false
  },
  "boundary": [
    "OBSERVATION_REPORT_ONLY",
    "SHADOW_RESEARCH_ONLY",
    "NOT_SIGNAL",
    "NO_TRADE_PROPOSAL",
    "NO_ENTRY_STOP_TARGET",
    "NO_RISK_OR_POSITION_SIZING",
    "NO_BROKER_EXECUTION",
    "NO_AUTO_EXECUTION",
    "NO_MEMORY_PROMOTION",
    "NO_RULE_REWRITE"
  ],
  "not_authorized": [
    "signal",
    "manual trade proposal",
    "entry/stop/target",
    "risk sizing",
    "broker/execution",
    "auto execution",
    "memory promotion",
    "rule rewrite"
  ],
  "next_allowed_use": "LIVE_SHADOW_OBSERVATION_REVIEW_ONLY"
}