{
  "created_utc": "2026-05-12T22:57:18Z",
  "authority": "READ_ONLY_M5_MERGE_NOT_SIGNAL",
  "results": [
    {
      "instrument": "EURUSD",
      "status": "MERGED",
      "old_rows": 6947,
      "incremental_rows": 58,
      "canonical_rows_after": 6949,
      "duplicates_removed": 56,
      "canonical_file": "data/live_m5/canonical/EURUSD_M5_canonical.csv.gz"
    },
    {
      "instrument": "USDJPY",
      "status": "MERGED",
      "old_rows": 7056,
      "incremental_rows": 58,
      "canonical_rows_after": 7058,
      "duplicates_removed": 56,
      "canonical_file": "data/live_m5/canonical/USDJPY_M5_canonical.csv.gz"
    },
    {
      "instrument": "XAUUSD",
      "status": "MERGED",
      "old_rows": 6908,
      "incremental_rows": 58,
      "canonical_rows_after": 6910,
      "duplicates_removed": 56,
      "canonical_file": "data/live_m5/canonical/XAUUSD_M5_canonical.csv.gz"
    }
  ]
}